testsexample/__init__.py
testsexample/atsfunc.py
testsexample/__pycache__/atsfunc.cpython-37.pyc
testsexample/__pycache__/debugtalk.cpython-37.pyc
testsexample/api/api_demo.yml
testsexample/data/user_agent.csv
testsexample/logs/2019_03_06.log
testsexample/logs/2019_03_06_20-48-21.log
testsexample/logs/2019_03_06_20-50-28.log
testsexample/logs/2019_03_06_20-51-08.log
testsexample/logs/2019_03_08_21-31-35.log
testsexample/logs/2019_03_08_21-42-11.log
testsexample/logs/2019_03_08_21-45-17.log
testsexample/logs/2019_03_08_22-12-46.log
testsexample/logs/2019_03_08_22-17-13.log
testsexample/logs/2019_03_08_22-18-08.log
testsexample/reports/1551862675.html
testsexample/reports/1551863819.html
testsexample/reports/1551863992.html
testsexample/reports/1551864060.html
testsexample/reports/1551864154.html
testsexample/reports/1551864702.html
testsexample/reports/1551864742.html
testsexample/reports/1551864914.html
testsexample/reports/1551866257.html
testsexample/reports/1551866365.html
testsexample/reports/1551870531.html
testsexample/reports/1551870621.html
testsexample/reports/1551870774.html
testsexample/reports/1551870940.html
testsexample/reports/1551871019.html
testsexample/reports/1551871055.html
testsexample/reports/1551871122.html
testsexample/reports/1551871160.html
testsexample/reports/1551871369.html
testsexample/reports/1551871421.html
testsexample/reports/1551872029.html
testsexample/reports/1551872053.html
testsexample/reports/1551872369.html
testsexample/reports/1551872520.html
testsexample/reports/1551873916.html
testsexample/reports/1551873964.html
testsexample/reports/1551874058.html
testsexample/reports/1551876501.html
testsexample/reports/1551876668.html
testsexample/reports/1552054688.html
testsexample/testcase/ref_csv_case_demo.yml
testsexample/testcase/testcase_demo.yml
testsexample/testsuite/ref_csv_suit_demo.yml
testsexample/testsuite/testsuit_demo.yml
zybats/__about__.py
zybats/__init__.py
zybats/api.py
zybats/built_in.py
zybats/cli.py
zybats-2.0.2.6.dist-info/LICENSE
zybats-2.0.2.6.dist-info/METADATA
zybats-2.0.2.6.dist-info/WHEEL
zybats-2.0.2.6.dist-info/entry_points.txt
zybats-2.0.2.6.dist-info/top_level.txt
zybats-2.0.2.6.dist-info/RECORD
