Metadata-Version: 2.1
Name: zybats
Version: 2.0.2.6
Summary: Automation Technical Service
Home-page: https://github.com/KinmieWang/ZYBATS
Author: zybqa
Author-email: kinmiewang@163.com
License: Apache-2.0
Keywords: HTTP api test requests locust
Platform: UNKNOWN
Classifier: Development Status :: 3 - Alpha
Classifier: Programming Language :: Python :: 2.7
Classifier: Programming Language :: Python :: 3.4
Classifier: Programming Language :: Python :: 3.5
Classifier: Programming Language :: Python :: 3.6
Classifier: Programming Language :: Python :: 3.7
Requires-Python: >=2.7, !=3.0.*, !=3.1.*, !=3.2.*, !=3.3.*, <4
Requires-Dist: requests
Requires-Dist: PyYAML
Requires-Dist: Jinja2
Requires-Dist: har2case
Requires-Dist: colorama
Requires-Dist: colorlog
Requires-Dist: requests-toolbelt
Requires-Dist: pika
Requires-Dist: redis (==2.10.6)
Requires-Dist: redis-py-cluster
Requires-Dist: xlrd
Requires-Dist: protobuf
Requires-Dist: simplejson
Requires-Dist: pymysql
Requires-Dist: Flask
Requires-Dist: MarkupSafe
Requires-Dist: certifi
Requires-Dist: chardet
Requires-Dist: idna
Requires-Dist: urllib3
